city_ch_autocomplete/admin.py
city_ch_autocomplete/apps.py
city_ch_autocomplete/forms.py
city_ch_autocomplete/models.py
city_ch_autocomplete/urls.py
city_ch_autocomplete/views.py
city_ch_autocomplete/locale/de/LC_MESSAGES/django.mo
city_ch_autocomplete/locale/de/LC_MESSAGES/django.po
city_ch_autocomplete/locale/fr/LC_MESSAGES/django.mo
city_ch_autocomplete/locale/fr/LC_MESSAGES/django.po
city_ch_autocomplete/locale/it/LC_MESSAGES/django.mo
city_ch_autocomplete/locale/it/LC_MESSAGES/django.po
city_ch_autocomplete/migrations/0001_initial.py
city_ch_autocomplete/migrations/0002_rename_indexes.py
city_ch_autocomplete/migrations/0003_plzdb_coord_x_coord_y.py
city_ch_autocomplete/migrations/__init__.py
city_ch_autocomplete/static/city_ch_autocomplete.js
city_ch_autocomplete-0.4.9.dist-info/licenses/LICENSE
city_ch_autocomplete-0.4.9.dist-info/METADATA
city_ch_autocomplete-0.4.9.dist-info/WHEEL
city_ch_autocomplete-0.4.9.dist-info/top_level.txt
city_ch_autocomplete-0.4.9.dist-info/RECORD
