Metadata-Version: 2.4
Name: city-ch-autocomplete
Version: 0.4.9
Summary: A Django app to query the Swiss Post API for postcodes and localities.
Author-email: Claude Paroz <claude@2xlibre.net>
Project-URL: Homepage, https://codeberg.org/claudep/city_ch_autocomplete
Classifier: Environment :: Web Environment
Classifier: Framework :: Django
Classifier: Intended Audience :: Developers
Classifier: License :: OSI Approved :: BSD License
Classifier: Operating System :: OS Independent
Classifier: Programming Language :: Python
Classifier: Programming Language :: Python :: 3
Classifier: Programming Language :: Python :: 3 :: Only
Classifier: Programming Language :: Python :: 3.9
Classifier: Programming Language :: Python :: 3.10
Classifier: Programming Language :: Python :: 3.11
Classifier: Programming Language :: Python :: 3.12
Classifier: Programming Language :: Python :: 3.13
Classifier: Topic :: Internet :: WWW/HTTP
Classifier: Topic :: Internet :: WWW/HTTP :: Dynamic Content
Requires-Python: >=3.9
License-File: LICENSE
Requires-Dist: httpx
Requires-Dist: django>=4.2
Dynamic: license-file
